README.md
setup.py
dftparse/__init__.py
dftparse/core.py
dftparse/util.py
dftparse.egg-info/PKG-INFO
dftparse.egg-info/SOURCES.txt
dftparse.egg-info/dependency_links.txt
dftparse.egg-info/top_level.txt
dftparse/pwscf/__init__.py
dftparse/pwscf/stdout_parser.py
dftparse/vasp/__init__.py
dftparse/vasp/eigenval_parser.py
dftparse/vasp/outcar_parser.py
dftparse/wien2k/__init__.py
dftparse/wien2k/absorp_parser.py
dftparse/wien2k/eloss_parser.py
dftparse/wien2k/epsilon_parser.py
dftparse/wien2k/reflectivity_parser.py
dftparse/wien2k/refract_parser.py
dftparse/wien2k/scf2_parser.py
dftparse/wien2k/scf_parser.py
dftparse/wien2k/sigmak_parser.py