Metadata-Version: 1.0
Name: dftparse
Version: 0.3.0
Summary: Library for parsing Density Functional Theory calculations
Home-page: https://github.com/CitrineInformatics/dftparse
Author: UNKNOWN
Author-email: UNKNOWN
License: UNKNOWN
Platform: UNKNOWN
